rtl/Cache.sv
// An 8-way set-associate test cache. 
// By Hakam Atassi, for the Mac-Risc-V team.


/*			Specifications
	*	
	*	Cache Size = 64 kB
	*	Set size = 8
	*	Block size = 16 bytes
	*	Word size = 64 bits
	*
	*		Therefore: 
	*	Lines = 512 lines
	*	Since 512 lines * 8 ways (blocks per line) * 4 words per block * 4 bytes per word = 64kB of data
	*	
*/


module Cache(
	input clock,
	input reset,
	input search_cache,
	input [31:0] address,
	output logic hit,
	output logic search_done,
	output logic [63:0] data,
	output logic [27:0] tag_out

);


parameter word_size=64;	//64 bit words
parameter block_size=4;	//4 words per block
parameter cache_capacity = 64*2^10;	//
parameter ways = 8;
parameter line_count = 512; 



initial begin
	$display("\nCache running!\n");
end



logic valid[line_count:0];
logic [26:0] tag[line_count:0];
logic [word_size*block_size:0] cache[line_count:0];


enum logic [1:0] {
	CACHE_IDLE,
	CACHE_CHECK_TAGS,
	CACHE_DONE
} CACHE_STATE;

//logic for determining if address is a hit
always_ff @(posedge clock, negedge reset) begin
		
	if(reset==1'b0) begin
		hit<=1'b0;
		search_done<=1'b0;
		CACHE_STATE<=CACHE_IDLE;
	end else begin
		
		case(CACHE_STATE)

			CACHE_IDLE: begin
				if(search_cache==1'b1) begin
					CACHE_STATE<=CACHE_CHECK_TAGS;
				end else begin
					CACHE_STATE<=CACHE_IDLE;
				end
				
				search_done<=1'b0;
			end

			CACHE_CHECK_TAGS: begin
				hit<=1'b0;
				for(integer i = 0; i < line_count; i=i+1) begin
					if(tag[i] == address) begin
						hit<=1'b1;
					end
				end

				CACHE_STATE<=CACHE_DONE;
			end

			CACHE_DONE: begin
				hit<=1'b0;
				search_done<=1'b1;
				CACHE_STATE<=CACHE_IDLE;
			end

		endcase
	end
end




always_ff @ (posedge clock, negedge reset) begin

	if(reset==1'b0) begin

		for(integer i = 0; i<line_count; i=i+1) begin
			valid[i]<=1'b0;
			tag[i]<=i[26:0];
			cache[i]<=i*i;
		end

	end else begin

		data<=cache[address];
		tag_out<=tag[address];

	end
end







	


endmodule

Cache_tb.sv
// Cache.sv Testbench

`include "Cache.sv"



module Cache_tb;

	logic clock;
	logic reset;
	logic [31:0] address;
	logic hit;
	logic search_cache;
	logic search_done;
	logic [63:0] data;
	logic [27:0] tag_out;

	Cache Cache(.clock(clock), .reset(reset), .search_cache(search_cache),
				.address(address), .hit(hit), .search_done(search_done), 
				.data(data), .tag_out(tag_out));


    initial begin
        $dumpfile("vcdDumpFiles/cache.vcd");
        $dumpvars;
    end


	initial begin
		$display("\nTestbench running!\n");
		$display("Triggering reset...");
		reset<=1'b1;
		address<=32'b0;


		@(posedge clock);
		reset<=1'b0;
		@(posedge clock);
		reset<=1'b1;
	end

	always begin
		clock<=1'b1; #1; 
		clock<=1'b0; #1;
	end
	

	always begin
		repeat (1500) @(posedge clock);
		$finish;
	end


	initial begin
	
			
		$display("\n\nCache is \"warmed\" with tags from 0->512 and data that is the square of the tag.");
		$display("ie: cache line 0 will contain Tag=0, Data=0*0=0");
		$display("    cache line 255 will contain Tag=255, Data=255*255=65025");
		$display("    cache line 1023 will miss, since it is not in memory (max tag is 511)\n");
		$display("    Note: each cache line actually contains words. The 4 words (64 bits each) are treated as one long word here.\n\n");



		repeat (15) @(posedge clock);	//wait for resets, inits, etc...
		/*********EXAMPLE HITS AND MISSES************/


		/**HIT (fetch address=0)**/
		search_cache<=1'b1;
		address<=32'd0;
		
		repeat (1) @(posedge clock);
		search_cache<=1'b0;
		repeat (2) @(posedge clock);	//wait for cache...

		$display("Address: %0d, Tag: %0d, Data: %0d, hit: %0d", address, tag_out, data, hit);
		


		/**HIT (fetch address=255)**/
		search_cache<=1'b1;
		address<=32'd255;
		
		repeat (1) @(posedge clock);
		search_cache<=1'b0;
		repeat (2) @(posedge clock);	//wait for cache...

		$display("Address: %0d, Tag: %0d, Data: %0d, hit: %0d", address, tag_out, data, hit);


		/**HIT (fetch address=511)**/
		search_cache<=1'b1;
		address<=32'd511;
		
		repeat (1) @(posedge clock);
		search_cache<=1'b0;
		repeat (2) @(posedge clock);	//wait for cache...

		$display("Address: %0d, Tag: %0d, Data: %0d, hit: %0d", address, tag_out, data, hit);

		/**MISS (fetch address=1024) **/
		search_cache<=1'b1;
		address<=32'd1023;
		
		repeat (1) @(posedge clock);
		search_cache<=1'b0;
		repeat (2) @(posedge clock);	//wait for cache...

		$display("Address: %0d, Tag: %0d, Data: %0d, hit: %0d", address, tag_out, data, hit);

	end


endmodule

vcdDumpFiles/cache.vcd
$date
	Mon Jan 23 20:44:37 2023
$end
$version
	Icarus Verilog
$end
$timescale
	1s
$end
$scope module Cache_tb $end
$var wire 28 ! tag_out [27:0] $end
$var wire 1 " search_done $end
$var wire 1 # hit $end
$var wire 64 $ data [63:0] $end
$var reg 32 % address [31:0] $end
$var reg 1 & clock $end
$var reg 1 ' reset $end
$var reg 1 ( search_cache $end
$scope module Cache $end
$var wire 32 ) address [31:0] $end
$var wire 1 & clock $end
$var wire 1 ' reset $end
$var wire 1 ( search_cache $end
$var reg 2 * CACHE_STATE [1:0] $end
$var reg 64 + data [63:0] $end
$var reg 1 # hit $end
$var reg 1 " search_done $end
$var reg 28 , tag_out [27:0] $end
$scope begin $ivl_for_loop0 $end
$var integer 32 - i [31:0] $end
$upscope $end
$scope begin $ivl_for_loop1 $end
$var integer 32 . i [31:0] $end
$upscope $end
$upscope $end
$upscope $end
$enddefinitions $end
#0
$dumpvars
b1000000000 .
bx -
b0xxxxxxxxxxxxxxxxxxxxxxxxxxx ,
bx +
b0 *
b0 )
x(
0'
1&
b0 %
bx $
0#
0"
b0xxxxxxxxxxxxxxxxxxxxxxxxxxx !
$end
#1
0&
#2
1'
b1000000000 .
1&
#3
0&
#4
b0 !
b0 ,
b0 $
b0 +
1&
#5
0&
#6
1&
#7
0&
#8
1&
#9
0&
#10
1&
#11
0&
#12
1&
#13
0&
#14
1&
#15
0&
#16
1&
#17
0&
#18
1&
#19
0&
#20
1&
#21
0&
#22
1&
#23
0&
#24
1&
#25
0&
#26
1&
#27
0&
#28
1(
1&
#29
0&
#30
b1 *
0(
1&
#31
0&
#32
b10 *
1#
b1000000000 -
1&
#33
0&
#34
b0 *
1"
0#
b11111111 %
b11111111 )
1(
1&
#35
0&
#36
0"
b1 *
b11111111 !
b11111111 ,
b1111111000000001 $
b1111111000000001 +
0(
1&
#37
0&
#38
b10 *
1#
b1000000000 -
1&
#39
0&
#40
b0 *
1"
0#
b111111111 %
b111111111 )
1(
1&
#41
0&
#42
0"
b1 *
b111111111 !
b111111111 ,
b111111110000000001 $
b111111110000000001 +
0(
1&
#43
0&
#44
b10 *
1#
b1000000000 -
1&
#45
0&
#46
b0 *
1"
0#
b1111111111 %
b1111111111 )
1(
1&
#47
0&
#48
0"
b1 *
b0xxxxxxxxxxxxxxxxxxxxxxxxxxx !
b0xxxxxxxxxxxxxxxxxxxxxxxxxxx ,
bx $
bx +
0(
1&
#49
0&
#50
b10 *
b1000000000 -
1&
#51
0&
#52
b0 *
1"
1&
#53
0&
#54
0"
1&
